{
    "description": "",
    "tags": [],
    "size": {
        "height": 760,
        "width": 570
    },
    "objects": [
        {
            "id": 77173906,
            "classId": 6489191,
            "description": "",
            "geometryType": "polygon",
            "labelerLogin": "inbox@datasetninja.com",
            "createdAt": "2023-10-30T12:40:50.961Z",
            "updatedAt": "2023-10-30T12:40:50.961Z",
            "tags": [
                {
                    "id": 44355542,
                    "tagId": 25648,
                    "name": "text",
                    "value": "WEST",
                    "labelerLogin": "inbox@datasetninja.com",
                    "createdAt": "2023-10-30T12:40:50.960Z",
                    "updatedAt": "2023-10-30T12:40:50.960Z"
                }
            ],
            "classTitle": "text",
            "points": {
                "exterior": [
                    [
                        35,
                        120
                    ],
                    [
                        48,
                        91
                    ],
                    [
                        56,
                        63
                    ],
                    [
                        66,
                        32
                    ],
                    [
                        85,
                        3
                    ],
                    [
                        117,
                        56
                    ],
                    [
                        105,
                        79
                    ],
                    [
                        99,
                        102
                    ],
                    [
                        96,
                        124
                    ],
                    [
                        91,
                        145
                    ]
                ],
                "interior": []
            }
        },
        {
            "id": 77173905,
            "classId": 6489191,
            "description": "",
            "geometryType": "polygon",
            "labelerLogin": "inbox@datasetninja.com",
            "createdAt": "2023-10-30T12:40:50.959Z",
            "updatedAt": "2023-10-30T12:40:50.959Z",
            "tags": [
                {
                    "id": 44355541,
                    "tagId": 25648,
                    "name": "text",
                    "value": "FOR",
                    "labelerLogin": "inbox@datasetninja.com",
                    "createdAt": "2023-10-30T12:40:50.959Z",
                    "updatedAt": "2023-10-30T12:40:50.959Z"
                }
            ],
            "classTitle": "text",
            "points": {
                "exterior": [
                    [
                        38,
                        172
                    ],
                    [
                        53,
                        182
                    ],
                    [
                        68,
                        191
                    ],
                    [
                        83,
                        197
                    ],
                    [
                        96,
                        206
                    ],
                    [
                        98,
                        240
                    ],
                    [
                        84,
                        233
                    ],
                    [
                        68,
                        226
                    ],
                    [
                        52,
                        215
                    ],
                    [
                        36,
                        212
                    ]
                ],
                "interior": []
            }
        },
        {
            "id": 77173904,
            "classId": 6489191,
            "description": "",
            "geometryType": "polygon",
            "labelerLogin": "inbox@datasetninja.com",
            "createdAt": "2023-10-30T12:40:50.959Z",
            "updatedAt": "2023-10-30T12:40:50.959Z",
            "tags": [
                {
                    "id": 44355540,
                    "tagId": 25648,
                    "name": "text",
                    "value": "CHEWING",
                    "labelerLogin": "inbox@datasetninja.com",
                    "createdAt": "2023-10-30T12:40:50.958Z",
                    "updatedAt": "2023-10-30T12:40:50.958Z"
                }
            ],
            "classTitle": "text",
            "points": {
                "exterior": [
                    [
                        94,
                        245
                    ],
                    [
                        113,
                        299
                    ],
                    [
                        129,
                        352
                    ],
                    [
                        152,
                        407
                    ],
                    [
                        199,
                        461
                    ],
                    [
                        192,
                        507
                    ],
                    [
                        122,
                        440
                    ],
                    [
                        83,
                        375
                    ],
                    [
                        59,
                        309
                    ],
                    [
                        47,
                        246
                    ]
                ],
                "interior": []
            }
        },
        {
            "id": 77173903,
            "classId": 6489191,
            "description": "",
            "geometryType": "polygon",
            "labelerLogin": "inbox@datasetninja.com",
            "createdAt": "2023-10-30T12:40:50.958Z",
            "updatedAt": "2023-10-30T12:40:50.958Z",
            "tags": [
                {
                    "id": 44355539,
                    "tagId": 25648,
                    "name": "text",
                    "value": "TOBACCO",
                    "labelerLogin": "inbox@datasetninja.com",
                    "createdAt": "2023-10-30T12:40:50.957Z",
                    "updatedAt": "2023-10-30T12:40:50.957Z"
                }
            ],
            "classTitle": "text",
            "points": {
                "exterior": [
                    [
                        126,
                        126
                    ],
                    [
                        169,
                        170
                    ],
                    [
                        213,
                        197
                    ],
                    [
                        256,
                        218
                    ],
                    [
                        299,
                        244
                    ],
                    [
                        289,
                        305
                    ],
                    [
                        244,
                        277
                    ],
                    [
                        202,
                        262
                    ],
                    [
                        158,
                        241
                    ],
                    [
                        116,
                        201
                    ]
                ],
                "interior": []
            }
        },
        {
            "id": 77173902,
            "classId": 6489191,
            "description": "",
            "geometryType": "polygon",
            "labelerLogin": "inbox@datasetninja.com",
            "createdAt": "2023-10-30T12:40:50.957Z",
            "updatedAt": "2023-10-30T12:40:50.957Z",
            "tags": [
                {
                    "id": 44355538,
                    "tagId": 25648,
                    "name": "text",
                    "value": "SMOKING",
                    "labelerLogin": "inbox@datasetninja.com",
                    "createdAt": "2023-10-30T12:40:50.957Z",
                    "updatedAt": "2023-10-30T12:40:50.957Z"
                }
            ],
            "classTitle": "text",
            "points": {
                "exterior": [
                    [
                        249,
                        455
                    ],
                    [
                        272,
                        421
                    ],
                    [
                        284,
                        385
                    ],
                    [
                        297,
                        350
                    ],
                    [
                        302,
                        317
                    ],
                    [
                        326,
                        326
                    ],
                    [
                        322,
                        368
                    ],
                    [
                        312,
                        411
                    ],
                    [
                        293,
                        453
                    ],
                    [
                        257,
                        495
                    ]
                ],
                "interior": []
            }
        },
        {
            "id": 77173901,
            "classId": 6489191,
            "description": "",
            "geometryType": "polygon",
            "labelerLogin": "inbox@datasetninja.com",
            "createdAt": "2023-10-30T12:40:50.956Z",
            "updatedAt": "2023-10-30T12:40:50.956Z",
            "tags": [
                {
                    "id": 44355537,
                    "tagId": 25648,
                    "name": "text",
                    "value": "#",
                    "labelerLogin": "inbox@datasetninja.com",
                    "createdAt": "2023-10-30T12:40:50.956Z",
                    "updatedAt": "2023-10-30T12:40:50.956Z"
                }
            ],
            "classTitle": "text",
            "points": {
                "exterior": [
                    [
                        103,
                        5
                    ],
                    [
                        218,
                        4
                    ],
                    [
                        235,
                        14
                    ],
                    [
                        232,
                        56
                    ],
                    [
                        172,
                        28
                    ],
                    [
                        127,
                        42
                    ]
                ],
                "interior": []
            }
        },
        {
            "id": 77173900,
            "classId": 6489191,
            "description": "",
            "geometryType": "polygon",
            "labelerLogin": "inbox@datasetninja.com",
            "createdAt": "2023-10-30T12:40:50.955Z",
            "updatedAt": "2023-10-30T12:40:50.955Z",
            "tags": [
                {
                    "id": 44355536,
                    "tagId": 25648,
                    "name": "text",
                    "value": "MAIL",
                    "labelerLogin": "inbox@datasetninja.com",
                    "createdAt": "2023-10-30T12:40:50.955Z",
                    "updatedAt": "2023-10-30T12:40:50.955Z"
                }
            ],
            "classTitle": "text",
            "points": {
                "exterior": [
                    [
                        248,
                        44
                    ],
                    [
                        266,
                        64
                    ],
                    [
                        278,
                        86
                    ],
                    [
                        287,
                        108
                    ],
                    [
                        296,
                        126
                    ],
                    [
                        280,
                        157
                    ],
                    [
                        275,
                        139
                    ],
                    [
                        265,
                        119
                    ],
                    [
                        254,
                        98
                    ],
                    [
                        233,
                        79
                    ]
                ],
                "interior": []
            }
        },
        {
            "id": 77173899,
            "classId": 6489191,
            "description": "",
            "geometryType": "polygon",
            "labelerLogin": "inbox@datasetninja.com",
            "createdAt": "2023-10-30T12:40:50.954Z",
            "updatedAt": "2023-10-30T12:40:50.954Z",
            "tags": [
                {
                    "id": 44355535,
                    "tagId": 25648,
                    "name": "text",
                    "value": "POUCH",
                    "labelerLogin": "inbox@datasetninja.com",
                    "createdAt": "2023-10-30T12:40:50.954Z",
                    "updatedAt": "2023-10-30T12:40:50.954Z"
                }
            ],
            "classTitle": "text",
            "points": {
                "exterior": [
                    [
                        297,
                        160
                    ],
                    [
                        310,
                        193
                    ],
                    [
                        316,
                        229
                    ],
                    [
                        321,
                        262
                    ],
                    [
                        322,
                        295
                    ],
                    [
                        299,
                        293
                    ],
                    [
                        299,
                        262
                    ],
                    [
                        296,
                        231
                    ],
                    [
                        289,
                        199
                    ],
                    [
                        277,
                        169
                    ]
                ],
                "interior": []
            }
        },
        {
            "id": 77173898,
            "classId": 6489191,
            "description": "",
            "geometryType": "polygon",
            "labelerLogin": "inbox@datasetninja.com",
            "createdAt": "2023-10-30T12:40:50.953Z",
            "updatedAt": "2023-10-30T12:40:50.953Z",
            "tags": [
                {
                    "id": 44355534,
                    "tagId": 25648,
                    "name": "text",
                    "value": "MARK",
                    "labelerLogin": "inbox@datasetninja.com",
                    "createdAt": "2023-10-30T12:40:50.953Z",
                    "updatedAt": "2023-10-30T12:40:50.953Z"
                }
            ],
            "classTitle": "text",
            "points": {
                "exterior": [
                    [
                        312,
                        120
                    ],
                    [
                        324,
                        149
                    ],
                    [
                        329,
                        181
                    ],
                    [
                        333,
                        210
                    ],
                    [
                        337,
                        238
                    ],
                    [
                        325,
                        244
                    ],
                    [
                        320,
                        216
                    ],
                    [
                        315,
                        188
                    ],
                    [
                        308,
                        158
                    ],
                    [
                        291,
                        129
                    ]
                ],
                "interior": []
            }
        },
        {
            "id": 77173897,
            "classId": 6489191,
            "description": "",
            "geometryType": "polygon",
            "labelerLogin": "inbox@datasetninja.com",
            "createdAt": "2023-10-30T12:40:50.952Z",
            "updatedAt": "2023-10-30T12:40:50.952Z",
            "tags": [
                {
                    "id": 44355533,
                    "tagId": 25648,
                    "name": "text",
                    "value": "BLOCH",
                    "labelerLogin": "inbox@datasetninja.com",
                    "createdAt": "2023-10-30T12:40:50.952Z",
                    "updatedAt": "2023-10-30T12:40:50.952Z"
                }
            ],
            "classTitle": "text",
            "points": {
                "exterior": [
                    [
                        345,
                        158
                    ],
                    [
                        377,
                        195
                    ],
                    [
                        410,
                        222
                    ],
                    [
                        440,
                        252
                    ],
                    [
                        473,
                        294
                    ],
                    [
                        474,
                        353
                    ],
                    [
                        440,
                        327
                    ],
                    [
                        409,
                        302
                    ],
                    [
                        378,
                        276
                    ],
                    [
                        345,
                        244
                    ]
                ],
                "interior": []
            }
        },
        {
            "id": 77173896,
            "classId": 6489191,
            "description": "",
            "geometryType": "polygon",
            "labelerLogin": "inbox@datasetninja.com",
            "createdAt": "2023-10-30T12:40:50.952Z",
            "updatedAt": "2023-10-30T12:40:50.952Z",
            "tags": [
                {
                    "id": 44355532,
                    "tagId": 25648,
                    "name": "text",
                    "value": "BROS",
                    "labelerLogin": "inbox@datasetninja.com",
                    "createdAt": "2023-10-30T12:40:50.951Z",
                    "updatedAt": "2023-10-30T12:40:50.951Z"
                }
            ],
            "classTitle": "text",
            "points": {
                "exterior": [
                    [
                        362,
                        293
                    ],
                    [
                        388,
                        315
                    ],
                    [
                        416,
                        332
                    ],
                    [
                        443,
                        347
                    ],
                    [
                        471,
                        371
                    ],
                    [
                        470,
                        425
                    ],
                    [
                        444,
                        419
                    ],
                    [
                        417,
                        409
                    ],
                    [
                        390,
                        396
                    ],
                    [
                        365,
                        385
                    ]
                ],
                "interior": []
            }
        },
        {
            "id": 77173895,
            "classId": 6489191,
            "description": "",
            "geometryType": "polygon",
            "labelerLogin": "inbox@datasetninja.com",
            "createdAt": "2023-10-30T12:40:50.951Z",
            "updatedAt": "2023-10-30T12:40:50.951Z",
            "tags": [
                {
                    "id": 44355531,
                    "tagId": 25648,
                    "name": "text",
                    "value": "WESTVIRGINIA",
                    "labelerLogin": "inbox@datasetninja.com",
                    "createdAt": "2023-10-30T12:40:50.951Z",
                    "updatedAt": "2023-10-30T12:40:50.951Z"
                }
            ],
            "classTitle": "text",
            "points": {
                "exterior": [
                    [
                        343,
                        417
                    ],
                    [
                        376,
                        427
                    ],
                    [
                        407,
                        436
                    ],
                    [
                        440,
                        443
                    ],
                    [
                        471,
                        450
                    ],
                    [
                        479,
                        504
                    ],
                    [
                        446,
                        494
                    ],
                    [
                        413,
                        493
                    ],
                    [
                        379,
                        491
                    ],
                    [
                        347,
                        493
                    ]
                ],
                "interior": []
            }
        },
        {
            "id": 77173894,
            "classId": 6489191,
            "description": "",
            "geometryType": "polygon",
            "labelerLogin": "inbox@datasetninja.com",
            "createdAt": "2023-10-30T12:40:50.950Z",
            "updatedAt": "2023-10-30T12:40:50.950Z",
            "tags": [
                {
                    "id": 44355530,
                    "tagId": 25648,
                    "name": "text",
                    "value": "MAIL",
                    "labelerLogin": "inbox@datasetninja.com",
                    "createdAt": "2023-10-30T12:40:50.950Z",
                    "updatedAt": "2023-10-30T12:40:50.950Z"
                }
            ],
            "classTitle": "text",
            "points": {
                "exterior": [
                    [
                        12,
                        562
                    ],
                    [
                        112,
                        546
                    ],
                    [
                        212,
                        544
                    ],
                    [
                        313,
                        533
                    ],
                    [
                        412,
                        529
                    ],
                    [
                        418,
                        647
                    ],
                    [
                        320,
                        696
                    ],
                    [
                        219,
                        758
                    ],
                    [
                        118,
                        759
                    ],
                    [
                        18,
                        752
                    ]
                ],
                "interior": []
            }
        },
        {
            "id": 77173893,
            "classId": 6489191,
            "description": "",
            "geometryType": "polygon",
            "labelerLogin": "inbox@datasetninja.com",
            "createdAt": "2023-10-30T12:40:50.949Z",
            "updatedAt": "2023-10-30T12:40:50.949Z",
            "tags": [
                {
                    "id": 44355529,
                    "tagId": 25648,
                    "name": "text",
                    "value": "POU",
                    "labelerLogin": "inbox@datasetninja.com",
                    "createdAt": "2023-10-30T12:40:50.948Z",
                    "updatedAt": "2023-10-30T12:40:50.948Z"
                }
            ],
            "classTitle": "text",
            "points": {
                "exterior": [
                    [
                        427,
                        520
                    ],
                    [
                        446,
                        522
                    ],
                    [
                        465,
                        522
                    ],
                    [
                        485,
                        522
                    ],
                    [
                        503,
                        521
                    ],
                    [
                        498,
                        593
                    ],
                    [
                        485,
                        600
                    ],
                    [
                        470,
                        609
                    ],
                    [
                        455,
                        622
                    ],
                    [
                        440,
                        627
                    ]
                ],
                "interior": []
            }
        },
        {
            "id": 77173892,
            "classId": 6489191,
            "description": "",
            "geometryType": "polygon",
            "labelerLogin": "inbox@datasetninja.com",
            "createdAt": "2023-10-30T12:40:50.948Z",
            "updatedAt": "2023-10-30T12:40:50.948Z",
            "tags": [
                {
                    "id": 44355528,
                    "tagId": 25648,
                    "name": "text",
                    "value": "#",
                    "labelerLogin": "inbox@datasetninja.com",
                    "createdAt": "2023-10-30T12:40:50.948Z",
                    "updatedAt": "2023-10-30T12:40:50.948Z"
                }
            ],
            "classTitle": "text",
            "points": {
                "exterior": [
                    [
                        299,
                        722
                    ],
                    [
                        505,
                        594
                    ],
                    [
                        507,
                        640
                    ],
                    [
                        344,
                        755
                    ],
                    [
                        292,
                        754
                    ]
                ],
                "interior": []
            }
        },
        {
            "id": 77173891,
            "classId": 6489191,
            "description": "",
            "geometryType": "polygon",
            "labelerLogin": "inbox@datasetninja.com",
            "createdAt": "2023-10-30T12:40:50.947Z",
            "updatedAt": "2023-10-30T12:40:50.947Z",
            "tags": [
                {
                    "id": 44355527,
                    "tagId": 25648,
                    "name": "text",
                    "value": "AND",
                    "labelerLogin": "inbox@datasetninja.com",
                    "createdAt": "2023-10-30T12:40:50.947Z",
                    "updatedAt": "2023-10-30T12:40:50.947Z"
                }
            ],
            "classTitle": "text",
            "points": {
                "exterior": [
                    [
                        207,
                        478
                    ],
                    [
                        217,
                        479
                    ],
                    [
                        226,
                        478
                    ],
                    [
                        237,
                        477
                    ],
                    [
                        245,
                        476
                    ],
                    [
                        244,
                        504
                    ],
                    [
                        233,
                        505
                    ],
                    [
                        223,
                        505
                    ],
                    [
                        214,
                        504
                    ],
                    [
                        204,
                        504
                    ]
                ],
                "interior": []
            }
        },
        {
            "id": 77173890,
            "classId": 6489191,
            "description": "",
            "geometryType": "polygon",
            "labelerLogin": "inbox@datasetninja.com",
            "createdAt": "2023-10-30T12:40:50.947Z",
            "updatedAt": "2023-10-30T12:40:50.947Z",
            "tags": [
                {
                    "id": 44355526,
                    "tagId": 25648,
                    "name": "text",
                    "value": "NTI",
                    "labelerLogin": "inbox@datasetninja.com",
                    "createdAt": "2023-10-30T12:40:50.947Z",
                    "updatedAt": "2023-10-30T12:40:50.947Z"
                }
            ],
            "classTitle": "text",
            "points": {
                "exterior": [
                    [
                        314,
                        6
                    ],
                    [
                        338,
                        8
                    ],
                    [
                        358,
                        39
                    ],
                    [
                        374,
                        60
                    ],
                    [
                        382,
                        77
                    ],
                    [
                        377,
                        127
                    ],
                    [
                        362,
                        107
                    ],
                    [
                        349,
                        86
                    ],
                    [
                        331,
                        63
                    ],
                    [
                        312,
                        41
                    ]
                ],
                "interior": []
            }
        },
        {
            "id": 77173889,
            "classId": 6489191,
            "description": "",
            "geometryType": "polygon",
            "labelerLogin": "inbox@datasetninja.com",
            "createdAt": "2023-10-30T12:40:50.946Z",
            "updatedAt": "2023-10-30T12:40:50.946Z",
            "tags": [
                {
                    "id": 44355525,
                    "tagId": 25648,
                    "name": "text",
                    "value": "#",
                    "labelerLogin": "inbox@datasetninja.com",
                    "createdAt": "2023-10-30T12:40:50.946Z",
                    "updatedAt": "2023-10-30T12:40:50.946Z"
                }
            ],
            "classTitle": "text",
            "points": {
                "exterior": [
                    [
                        394,
                        100
                    ],
                    [
                        417,
                        122
                    ],
                    [
                        432,
                        144
                    ],
                    [
                        447,
                        168
                    ],
                    [
                        457,
                        189
                    ],
                    [
                        447,
                        220
                    ],
                    [
                        431,
                        203
                    ],
                    [
                        420,
                        188
                    ],
                    [
                        407,
                        173
                    ],
                    [
                        388,
                        156
                    ]
                ],
                "interior": []
            }
        }
    ]
}