{
    "description": "",
    "tags": [],
    "size": {
        "height": 500,
        "width": 500
    },
    "objects": [
        {
            "id": 77175383,
            "classId": 6489191,
            "description": "",
            "geometryType": "polygon",
            "labelerLogin": "inbox@datasetninja.com",
            "createdAt": "2023-10-30T12:41:17.327Z",
            "updatedAt": "2023-10-30T12:41:17.327Z",
            "tags": [
                {
                    "id": 44357019,
                    "tagId": 25648,
                    "name": "text",
                    "value": "GARy",
                    "labelerLogin": "inbox@datasetninja.com",
                    "createdAt": "2023-10-30T12:41:17.326Z",
                    "updatedAt": "2023-10-30T12:41:17.326Z"
                }
            ],
            "classTitle": "text",
            "points": {
                "exterior": [
                    [
                        187,
                        257
                    ],
                    [
                        200,
                        262
                    ],
                    [
                        213,
                        266
                    ],
                    [
                        227,
                        267
                    ],
                    [
                        240,
                        271
                    ],
                    [
                        236,
                        286
                    ],
                    [
                        225,
                        286
                    ],
                    [
                        212,
                        282
                    ],
                    [
                        199,
                        276
                    ],
                    [
                        186,
                        276
                    ]
                ],
                "interior": []
            }
        },
        {
            "id": 77175382,
            "classId": 6489191,
            "description": "",
            "geometryType": "polygon",
            "labelerLogin": "inbox@datasetninja.com",
            "createdAt": "2023-10-30T12:41:17.326Z",
            "updatedAt": "2023-10-30T12:41:17.326Z",
            "tags": [
                {
                    "id": 44357018,
                    "tagId": 25648,
                    "name": "text",
                    "value": "DANKO",
                    "labelerLogin": "inbox@datasetninja.com",
                    "createdAt": "2023-10-30T12:41:17.326Z",
                    "updatedAt": "2023-10-30T12:41:17.326Z"
                }
            ],
            "classTitle": "text",
            "points": {
                "exterior": [
                    [
                        250,
                        279
                    ],
                    [
                        270,
                        286
                    ],
                    [
                        287,
                        292
                    ],
                    [
                        304,
                        300
                    ],
                    [
                        320,
                        309
                    ],
                    [
                        316,
                        326
                    ],
                    [
                        296,
                        314
                    ],
                    [
                        277,
                        306
                    ],
                    [
                        258,
                        299
                    ],
                    [
                        239,
                        294
                    ]
                ],
                "interior": []
            }
        },
        {
            "id": 77175381,
            "classId": 6489191,
            "description": "",
            "geometryType": "polygon",
            "labelerLogin": "inbox@datasetninja.com",
            "createdAt": "2023-10-30T12:41:17.325Z",
            "updatedAt": "2023-10-30T12:41:17.325Z",
            "tags": [
                {
                    "id": 44357017,
                    "tagId": 25648,
                    "name": "text",
                    "value": "SAN",
                    "labelerLogin": "inbox@datasetninja.com",
                    "createdAt": "2023-10-30T12:41:17.325Z",
                    "updatedAt": "2023-10-30T12:41:17.325Z"
                }
            ],
            "classTitle": "text",
            "points": {
                "exterior": [
                    [
                        193,
                        274
                    ],
                    [
                        198,
                        280
                    ],
                    [
                        202,
                        285
                    ],
                    [
                        206,
                        290
                    ],
                    [
                        212,
                        291
                    ],
                    [
                        202,
                        305
                    ],
                    [
                        196,
                        301
                    ],
                    [
                        190,
                        295
                    ],
                    [
                        185,
                        289
                    ],
                    [
                        179,
                        282
                    ]
                ],
                "interior": []
            }
        },
        {
            "id": 77175380,
            "classId": 6489191,
            "description": "",
            "geometryType": "polygon",
            "labelerLogin": "inbox@datasetninja.com",
            "createdAt": "2023-10-30T12:41:17.324Z",
            "updatedAt": "2023-10-30T12:41:17.324Z",
            "tags": [
                {
                    "id": 44357016,
                    "tagId": 25648,
                    "name": "text",
                    "value": "FRANCISCO",
                    "labelerLogin": "inbox@datasetninja.com",
                    "createdAt": "2023-10-30T12:41:17.324Z",
                    "updatedAt": "2023-10-30T12:41:17.324Z"
                }
            ],
            "classTitle": "text",
            "points": {
                "exterior": [
                    [
                        218,
                        295
                    ],
                    [
                        241,
                        306
                    ],
                    [
                        262,
                        314
                    ],
                    [
                        284,
                        317
                    ],
                    [
                        305,
                        318
                    ],
                    [
                        311,
                        333
                    ],
                    [
                        285,
                        333
                    ],
                    [
                        259,
                        330
                    ],
                    [
                        231,
                        321
                    ],
                    [
                        206,
                        310
                    ]
                ],
                "interior": []
            }
        },
        {
            "id": 77175379,
            "classId": 6489191,
            "description": "",
            "geometryType": "polygon",
            "labelerLogin": "inbox@datasetninja.com",
            "createdAt": "2023-10-30T12:41:17.324Z",
            "updatedAt": "2023-10-30T12:41:17.324Z",
            "tags": [
                {
                    "id": 44357015,
                    "tagId": 25648,
                    "name": "text",
                    "value": "G",
                    "labelerLogin": "inbox@datasetninja.com",
                    "createdAt": "2023-10-30T12:41:17.323Z",
                    "updatedAt": "2023-10-30T12:41:17.323Z"
                }
            ],
            "classTitle": "text",
            "points": {
                "exterior": [
                    [
                        215,
                        214
                    ],
                    [
                        241,
                        221
                    ],
                    [
                        266,
                        226
                    ],
                    [
                        290,
                        233
                    ],
                    [
                        314,
                        242
                    ],
                    [
                        303,
                        289
                    ],
                    [
                        279,
                        282
                    ],
                    [
                        254,
                        273
                    ],
                    [
                        229,
                        264
                    ],
                    [
                        204,
                        257
                    ]
                ],
                "interior": []
            }
        }
    ]
}